{
"companyName": "GDUT",
"productName": "STUPID BIRD",
"productVersion": "0.1",
"dataUrl": "hhyyy.data.unityweb",
"wasmCodeUrl": "hhyyy.wasm.code.unityweb",
"wasmFrameworkUrl": "hhyyy.wasm.framework.unityweb",
"graphicsAPI": ["WebGL 2.0","WebGL 1.0"],
"webglContextAttributes": {"preserveDrawingBuffer": false},
"backgroundUrl": "hhyyy.jpg",
"splashScreenStyle": "Dark",
"backgroundColor": "#FFFFFF",
"cacheControl": {"default": "must-revalidate"},
"developmentBuild": false,
"multithreading": false,
"unityVersion": "2019.2.0f1"
}